rtl/alu.v
module alu (
    input  [31:0] a,
    input  [31:0] b,
    input  [2:0] alu_control,
    output reg [31:0] result
);

always @(*) begin
    case (alu_control)
        3'b000: result = a + b; // ADD
        3'b001: result = a - b; // SUB
        3'b010: result = a & b; // AND
        3'b011: result = a | b; // OR
        default: result = 32'd0;
    endcase
end

endmodule

rtl/register_file.v
module register_file(
    input clk,
    input rst,              // ⭐ MUST EXIST
    input reg_write,
    input [4:0] rs1,
    input [4:0] rs2,
    input [4:0] rd,
    input [31:0] write_data,
    output [31:0] read_data1,
    output [31:0] read_data2
);

reg [31:0] regs[0:31];
integer i;

// ---------- RESET + WRITE ----------
always @(posedge clk or posedge rst) begin
    if (rst) begin
        for(i=0;i<32;i=i+1)
            regs[i] <= 32'b0;   // ⭐ CRITICAL FIX
    end
    else if(reg_write && rd!=0) begin
        regs[rd] <= write_data;
    end
end

// ---------- READ ----------
assign read_data1 = regs[rs1];
assign read_data2 = regs[rs2];

endmodule

rtl/control_unit.v
module control_unit(
    input [6:0] opcode,
    output reg reg_write,
    output reg mem_read,
    output reg mem_write,
    output reg [2:0] alu_control
);

always @(*) begin

    // default values
    reg_write = 0;
    mem_read = 0;
    mem_write = 0;
    alu_control = 3'b000;

    case(opcode)

        // R-type
        7'b0110011: begin
            reg_write = 1;
            alu_control = 3'b010;
        end

        // I-type (ADDI) ⭐ THIS IS YOUR INSTRUCTION
        7'b0010011: begin
            reg_write = 1;
            alu_control = 3'b010;
        end

        default: begin
            reg_write = 0;
        end

    endcase
end

endmodule

rtl/instruction_memory.v
module instruction_memory (
    input  [31:0] addr,
    output [31:0] instruction
);

reg [31:0] memory [0:255];

initial begin
    $readmemh("sim/program.mem", memory);
end

// IMPORTANT: word addressing
assign instruction = memory[addr[31:2]];

endmodule

rtl/pc.v
module pc (
    input clk,
    input rst,
    output reg [31:0] pc_out
);

always @(posedge clk or posedge rst) begin
    if (rst)
        pc_out <= 0;      // reset PC to 0
    else
        pc_out <= pc_out + 4; // next instruction
end

endmodule

rtl/if_id_reg.v
module if_id_reg (
    input clk,
    input rst,

    input [31:0] pc_in,
    input [31:0] instr_in,

    output reg [31:0] pc_out,
    output reg [31:0] instr_out
);

always @(posedge clk or posedge rst) begin
    if (rst) begin
        pc_out    <= 0;
        instr_out <= 0;
    end
    else begin
        pc_out    <= pc_in;
        instr_out <= instr_in;
    end
end

endmodule

rtl/cpu_top.v
module cpu_top (
    input clk,
    input rst
);

// -------- wires ----------
wire [31:0] pc_out;
wire [31:0] instruction;

wire reg_write;
wire mem_read;
wire mem_write;
wire [2:0] alu_control;

wire [31:0] read_data1, read_data2;
wire [31:0] alu_result;

wire [31:0] if_pc;
wire [31:0] if_instr;

wire [31:0] id_pc;
wire [31:0] id_instr;

// ---------- IF stage ----------
assign if_pc    = pc_out;
assign if_instr = instruction;

// -------- IF/ID Pipeline Register ----------
if_id_reg ifid (
    .clk(clk),
    .rst(rst),
    .pc_in(if_pc),
    .instr_in(if_instr),
    .pc_out(id_pc),
    .instr_out(id_instr)
);

// -------- PC ----------
pc pc_inst (
    .clk(clk),
    .rst(rst),
    .pc_out(pc_out)
);

// -------- Instruction Memory ----------
instruction_memory imem (
    .addr(pc_out),      // PC fetch
    .instruction(instruction)
);

// -------- Control Unit ----------
control_unit cu (
    .opcode(id_instr[6:0]),
    .reg_write(reg_write),
    .mem_read(mem_read),
    .mem_write(mem_write),
    .alu_control(alu_control)
);

// -------- Register File ----------
register_file rf (
    .clk(clk),
    .rst(rst),                     // ⭐ FIX 1 (VERY IMPORTANT)
    .reg_write(reg_write),
    .rs1(id_instr[19:15]),
    .rs2(id_instr[24:20]),
    .rd(id_instr[11:7]),
    .write_data(alu_result),
    .read_data1(read_data1),
    .read_data2(read_data2)
);

// -------- ALU ----------
alu alu_inst (
    .a(read_data1),
    .b(read_data2),
    .alu_control(alu_control),
    .result(alu_result)
);

endmodule

testbench/cpu_top_tb.v
module cpu_top_tb;

reg clk;
reg rst;

// ---------- DUT ----------
cpu_top uut (
    .clk(clk),
    .rst(rst)
);

// ---------- Clock Generation ----------
initial begin
    clk = 0;
    forever #5 clk = ~clk;   // 10ns clock
end

// ---------- Reset ----------
initial begin
    rst = 1;
    #20;
    rst = 0;                 // release reset
end

// ---------- Waveform Dump ----------
initial begin
    $dumpfile("cpu.vcd");
    $dumpvars(0, cpu_top_tb);
end

// ---------- DEBUG MONITOR (VERY IMPORTANT) ----------
initial begin
    $monitor(
      "T=%0t PC=%h INSTR=%h RS1=%h RS2=%h ALU=%h ALUCTRL=%b REGWRITE=%b",
      $time,
      uut.pc_out,
      uut.instruction,
      uut.read_data1,
      uut.read_data2,
      uut.alu_result,
      uut.alu_control,
      uut.reg_write
    );
end

// ---------- Stop Simulation ----------
initial begin
    #200;
    $finish;
end

endmodule

cpu.vcd
$date
	Sat Feb 28 18:07:04 2026
$end
$version
	Icarus Verilog
$end
$timescale
	1s
$end
$scope module cpu_top_tb $end
$var reg 1 ! clk $end
$var reg 1 " rst $end
$scope module uut $end
$var wire 1 ! clk $end
$var wire 32 # if_instr [31:0] $end
$var wire 32 $ if_pc [31:0] $end
$var wire 1 " rst $end
$var wire 1 % reg_write $end
$var wire 32 & read_data2 [31:0] $end
$var wire 32 ' read_data1 [31:0] $end
$var wire 32 ( pc_out [31:0] $end
$var wire 1 ) mem_write $end
$var wire 1 * mem_read $end
$var wire 32 + instruction [31:0] $end
$var wire 32 , id_pc [31:0] $end
$var wire 32 - id_instr [31:0] $end
$var wire 32 . alu_result [31:0] $end
$var wire 3 / alu_control [2:0] $end
$scope module alu_inst $end
$var wire 32 0 b [31:0] $end
$var wire 3 1 alu_control [2:0] $end
$var wire 32 2 a [31:0] $end
$var reg 32 3 result [31:0] $end
$upscope $end
$scope module cu $end
$var wire 7 4 opcode [6:0] $end
$var reg 3 5 alu_control [2:0] $end
$var reg 1 * mem_read $end
$var reg 1 ) mem_write $end
$var reg 1 % reg_write $end
$upscope $end
$scope module ifid $end
$var wire 1 ! clk $end
$var wire 32 6 instr_in [31:0] $end
$var wire 32 7 pc_in [31:0] $end
$var wire 1 " rst $end
$var reg 32 8 instr_out [31:0] $end
$var reg 32 9 pc_out [31:0] $end
$upscope $end
$scope module imem $end
$var wire 32 : instruction [31:0] $end
$var wire 32 ; addr [31:0] $end
$upscope $end
$scope module pc_inst $end
$var wire 1 ! clk $end
$var wire 1 " rst $end
$var reg 32 < pc_out [31:0] $end
$upscope $end
$scope module rf $end
$var wire 1 ! clk $end
$var wire 5 = rd [4:0] $end
$var wire 32 > read_data1 [31:0] $end
$var wire 32 ? read_data2 [31:0] $end
$var wire 1 % reg_write $end
$var wire 5 @ rs1 [4:0] $end
$var wire 5 A rs2 [4:0] $end
$var wire 1 " rst $end
$var wire 32 B write_data [31:0] $end
$var integer 32 C i [31:0] $end
$upscope $end
$upscope $end
$upscope $end
$enddefinitions $end
#0
$dumpvars
b100000 C
b0 B
b0 A
b0 @
b0 ?
b0 >
b0 =
b0 <
b0 ;
b100000000000010010011 :
b0 9
b0 8
b0 7
b100000000000010010011 6
b0 5
b0 4
b0 3
b0 2
b0 1
b0 0
b0 /
b0 .
b0 -
b0 ,
b100000000000010010011 +
0*
0)
b0 (
b0 '
b0 &
0%
b0 $
b100000000000010010011 #
1"
0!
$end
#5
b100000 C
1!
#10
0!
#15
b100000 C
1!
#20
0!
0"
#25
b10 /
b10 1
b10 5
1%
b1000000000000100010011 #
b1000000000000100010011 6
b1000000000000100010011 +
b1000000000000100010011 :
b1 =
b1 A
b10011 4
b100 $
b100 7
b100 (
b100 ;
b100 <
b100000000000010010011 -
b100000000000010010011 8
1!
#30
0!
#35
b10 =
b10 A
b1100001000000110010011 #
b1100001000000110010011 6
b1100001000000110010011 +
b1100001000000110010011 :
b1000000000000100010011 -
b1000000000000100010011 8
b100 ,
b100 9
b1000 $
b1000 7
b1000 (
b1000 ;
b1000 <
1!
#40
0!
#45
bx #
bx 6
bx +
bx :
b11 =
b11 A
b1 @
b1100 $
b1100 7
b1100 (
b1100 ;
b1100 <
b1100001000000110010011 -
b1100001000000110010011 8
b1000 ,
b1000 9
1!
#50
0!
#55
bx .
bx 3
bx B
b0 /
b0 1
b0 5
0%
bx =
bx &
bx 0
bx ?
bx A
bx '
bx 2
bx >
bx @
bx 4
bx -
bx 8
b1100 ,
b1100 9
b10000 $
b10000 7
b10000 (
b10000 ;
b10000 <
1!
#60
0!
#65
b10100 $
b10100 7
b10100 (
b10100 ;
b10100 <
b10000 ,
b10000 9
1!
#70
0!
#75
b10100 ,
b10100 9
b11000 $
b11000 7
b11000 (
b11000 ;
b11000 <
1!
#80
0!
#85
b11100 $
b11100 7
b11100 (
b11100 ;
b11100 <
b11000 ,
b11000 9
1!
#90
0!
#95
b11100 ,
b11100 9
b100000 $
b100000 7
b100000 (
b100000 ;
b100000 <
1!
#100
0!
#105
b100100 $
b100100 7
b100100 (
b100100 ;
b100100 <
b100000 ,
b100000 9
1!
#110
0!
#115
b100100 ,
b100100 9
b101000 $
b101000 7
b101000 (
b101000 ;
b101000 <
1!
#120
0!
#125
b101100 $
b101100 7
b101100 (
b101100 ;
b101100 <
b101000 ,
b101000 9
1!
#130
0!
#135
b101100 ,
b101100 9
b110000 $
b110000 7
b110000 (
b110000 ;
b110000 <
1!
#140
0!
#145
b110100 $
b110100 7
b110100 (
b110100 ;
b110100 <
b110000 ,
b110000 9
1!
#150
0!
#155
b110100 ,
b110100 9
b111000 $
b111000 7
b111000 (
b111000 ;
b111000 <
1!
#160
0!
#165
b111100 $
b111100 7
b111100 (
b111100 ;
b111100 <
b111000 ,
b111000 9
1!
#170
0!
#175
b111100 ,
b111100 9
b1000000 $
b1000000 7
b1000000 (
b1000000 ;
b1000000 <
1!
#180
0!
#185
b1000100 $
b1000100 7
b1000100 (
b1000100 ;
b1000100 <
b1000000 ,
b1000000 9
1!
#190
0!
#195
b1000100 ,
b1000100 9
b1001000 $
b1001000 7
b1001000 (
b1001000 ;
b1001000 <
1!
