rtl/pc.v
module pc (
    input clk,
    input rst,
    output reg [31:0] pc_out
);

always @(posedge clk or posedge rst) begin
    if (rst)
        pc_out <= 0;      // reset PC to 0
    else
        pc_out <= pc_out + 4; // next instruction
end

endmodule

testbench/pc_tb.v
module pc_tb;

reg clk;
reg rst;
wire [31:0] pc_out;

pc uut (
    .clk(clk),
    .rst(rst),
    .pc_out(pc_out)
);

// clock generation
always #5 clk = ~clk;

initial begin
    $dumpfile("pc.vcd");
    $dumpvars(0, pc_tb);

    clk = 0;
    rst = 1;

    #10 rst = 0;   // release reset

    #100 $finish;
end

endmodule

pc.vcd
$date
	Fri Feb 27 20:19:29 2026
$end
$version
	Icarus Verilog
$end
$timescale
	1s
$end
$scope module pc_tb $end
$var wire 32 ! pc_out [31:0] $end
$var reg 1 " clk $end
$var reg 1 # rst $end
$scope module uut $end
$var wire 1 " clk $end
$var wire 1 # rst $end
$var reg 32 $ pc_out [31:0] $end
$upscope $end
$upscope $end
$enddefinitions $end
#0
$dumpvars
b0 $
1#
0"
b0 !
$end
#5
1"
#10
0"
0#
#15
b100 !
b100 $
1"
#20
0"
#25
b1000 !
b1000 $
1"
#30
0"
#35
b1100 !
b1100 $
1"
#40
0"
#45
b10000 !
b10000 $
1"
#50
0"
#55
b10100 !
b10100 $
1"
#60
0"
#65
b11000 !
b11000 $
1"
#70
0"
#75
b11100 !
b11100 $
1"
#80
0"
#85
b100000 !
b100000 $
1"
#90
0"
#95
b100100 !
b100100 $
1"
#100
0"
#105
b101000 !
b101000 $
1"
